lingpy/README.md
lingpy/__init__.py
lingpy/__main__.py
lingpy/_settings.py
lingpy/basictypes.py
lingpy/cache.py
lingpy/cli.py
lingpy/config.py
lingpy/log.py
lingpy/settings.py
lingpy/util.py
lingpy/algorithm/__init__.py
lingpy/algorithm/_tree.py
lingpy/algorithm/cluster_util.py
lingpy/algorithm/clustering.py
lingpy/algorithm/extra.py
lingpy/algorithm/cython/__init__.py
lingpy/algorithm/cython/_calign.py
lingpy/algorithm/cython/_cluster.py
lingpy/algorithm/cython/_malign.py
lingpy/algorithm/cython/_misc.py
lingpy/algorithm/cython/_talign.py
lingpy/align/__init__.py
lingpy/align/multiple.py
lingpy/align/pairwise.py
lingpy/align/sca.py
lingpy/align/_align/__init__.py
lingpy/align/_align/confidence.py
lingpy/basic/__init__.py
lingpy/basic/ops.py
lingpy/basic/parser.py
lingpy/basic/tree.py
lingpy/basic/wordlist.py
lingpy/compare/__init__.py
lingpy/compare/_structure.py
lingpy/compare/lexstat.py
lingpy/compare/partial.py
lingpy/compare/phylogeny.py
lingpy/compare/sanity.py
lingpy/compare/strings.py
lingpy/compare/util.py
lingpy/compare/_phylogeny/__init__.py
lingpy/compare/_phylogeny/_settings.py
lingpy/compare/_phylogeny/convex_hull.py
lingpy/compare/_phylogeny/polygon.py
lingpy/compare/_phylogeny/utils.py
lingpy/convert/__init__.py
lingpy/convert/cldf.py
lingpy/convert/graph.py
lingpy/convert/html.py
lingpy/convert/plot.py
lingpy/convert/strings.py
lingpy/convert/tree.py
lingpy/data/__init__.py
lingpy/data/derive.py
lingpy/data/model.py
lingpy/data/conf/dictionary.rc
lingpy/data/conf/qlc.rc
lingpy/data/conf/swadesh.rc
lingpy/data/conf/wordlist.rc
lingpy/data/ipa/__init__.py
lingpy/data/ipa/sampa.csv
lingpy/data/ipa/sampa.py
lingpy/data/models/art/INFO
lingpy/data/models/art/converter
lingpy/data/models/art_el/INFO
lingpy/data/models/art_el/converter
lingpy/data/models/asjp/INFO
lingpy/data/models/asjp/asjp.py
lingpy/data/models/asjp/asjp_score_dict.csv
lingpy/data/models/asjp/cons_score
lingpy/data/models/asjp/converter
lingpy/data/models/asjp/matrix
lingpy-2.6.13.dist-info/LICENSE
lingpy-2.6.13.dist-info/METADATA
lingpy-2.6.13.dist-info/WHEEL
lingpy-2.6.13.dist-info/entry_points.txt
lingpy-2.6.13.dist-info/top_level.txt
lingpy-2.6.13.dist-info/RECORD
