Metadata-Version: 2.1
Name: lingpy
Version: 2.6.13
Summary: Python library for quantitative tasks in historical linguistics
Home-page: https://lingpy.org
Author: Johann-Mattis List and Robert Forkel
Author-email: info@lingpy.org
License: gpl-3.0
Keywords: linguistics,sequence alignment,computational linguistics,dialectology,cognate detection
Platform: any
Classifier: Development Status :: 5 - Production/Stable
Classifier: Intended Audience :: Developers
Classifier: Intended Audience :: Science/Research
Classifier: Natural Language :: English
Classifier: Operating System :: OS Independent
Classifier: Programming Language :: Python :: 3
Classifier: Programming Language :: Python :: 3.8
Classifier: Programming Language :: Python :: 3.9
Classifier: Programming Language :: Python :: 3.10
Classifier: Programming Language :: Python :: 3.11
Classifier: Programming Language :: Python :: Implementation :: CPython
Classifier: Programming Language :: Python :: Implementation :: PyPy
Classifier: License :: OSI Approved :: GNU General Public License v3 (GPLv3)
Requires-Python: >=3.8
Provides-Extra: dev
Provides-Extra: test
Provides-Extra: cluster
Provides-Extra: borrowing
License-File: LICENSE
